{
  "Version": "2012-10-17",
  "Statement": [
    {
      "Sid": "AdminMinimal",
      "Effect": "Allow",
      "Action": [
        "kafka-cluster:Connect",
        "kafka-cluster:DescribeCluster",
        "kafka-cluster:CreateTopic",
        "kafka-cluster:AlterTopic",
        "kafka-cluster:DeleteTopic",
        "kafka-cluster:DescribeTopic",
        "kafka-cluster:WriteData",
        "kafka-cluster:ReadData",
        "kafka-cluster:DescribeGroup",
        "kafka-cluster:AlterGroup"
      ],
      "Resource": [
        "arn:aws:kafka:*:*:cluster/*",
        "arn:aws:kafka:*:*:topic/*/*",
        "arn:aws:kafka:*:*:group/*/*"
      ]
    }
  ]
}
